setup.py
yadage_haiku.egg-info/PKG-INFO
yadage_haiku.egg-info/SOURCES.txt
yadage_haiku.egg-info/dependency_links.txt
yadage_haiku.egg-info/entry_points.txt
yadage_haiku.egg-info/requires.txt
yadage_haiku.egg-info/top_level.txt
yadagehaiku/__init__.py