Metadata-Version: 1.0
Name: yadage-haiku
Version: 0.99.0
Summary: yadage-haiku - a very concise dialect of yadage.
Home-page: UNKNOWN
Author: Lukas Heinrich
Author-email: lukas.heinrich@cern.ch
License: UNKNOWN
Platform: UNKNOWN
